cawlib/__init__.py
cawlib/cawlib.cpython-312-aarch64-linux-musl.so
cawlib-0.0.5.dist-info/METADATA
cawlib-0.0.5.dist-info/WHEEL
cawlib.libs/libgcc_s-9d28dc04.so.1
cawlib-0.0.5.dist-info/RECORD
