Metadata-Version: 2.4
Name: cawlib
Version: 0.0.5
Classifier: Programming Language :: Rust
Classifier: Programming Language :: Python :: Implementation :: CPython
Classifier: Programming Language :: Python :: Implementation :: PyPy
Summary: A library for robot control
Author-email: noxrick91 <noxrick91@gmail.com>
License: Proprietary - All rights reserved
Requires-Python: >=3.8
